{
  "main": {
    "id": "53034b76338d2d0e",
    "type": "split",
    "children": [
      {
        "id": "4fb90a3c88163047",
        "type": "tabs",
        "children": [
          {
            "id": "ae72f1b6abe14242",
            "type": "leaf",
            "state": {
              "type": "markdown",
              "state": {
                "file": "4 - Webpack & 工具链/babel原理综述.md",
                "mode": "preview",
                "backlinks": false,
                "source": false
              }
            }
          }
        ]
      }
    ],
    "direction": "vertical"
  },
  "left": {
    "id": "5d37b1d6c9a834d2",
    "type": "split",
    "children": [
      {
        "id": "53be009034134e1e",
        "type": "tabs",
        "children": [
          {
            "id": "69248991cb63ec3f",
            "type": "leaf",
            "state": {
              "type": "file-explorer",
              "state": {
                "sortOrder": "custom"
              }
            }
          },
          {
            "id": "bf0684ec9665fc1e",
            "type": "leaf",
            "state": {
              "type": "search",
              "state": {
                "query": "",
                "matchingCase": false,
                "explainSearch": false,
                "collapseAll": false,
                "extraContext": false,
                "sortOrder": "alphabetical"
              }
            }
          },
          {
            "id": "7e4c770f558ff9cf",
            "type": "leaf",
            "state": {
              "type": "bookmarks",
              "state": {}
            }
          }
        ]
      }
    ],
    "direction": "horizontal",
    "width": 247.5110321044922
  },
  "right": {
    "id": "2114abde7063af78",
    "type": "split",
    "children": [
      {
        "id": "91d4460fcc49b966",
        "type": "tabs",
        "children": [
          {
            "id": "e52b1cd3f9e79746",
            "type": "leaf",
            "state": {
              "type": "backlink",
              "state": {
                "file": "4 - Webpack & 工具链/babel原理综述.md",
                "collapseAll": false,
                "extraContext": false,
                "sortOrder": "alphabetical",
                "showSearch": false,
                "searchQuery": "",
                "backlinkCollapsed": false,
                "unlinkedCollapsed": true
              }
            }
          },
          {
            "id": "811a493565cf9f65",
            "type": "leaf",
            "state": {
              "type": "outgoing-link",
              "state": {
                "file": "4 - Webpack & 工具链/babel原理综述.md",
                "linksCollapsed": false,
                "unlinkedCollapsed": true
              }
            }
          },
          {
            "id": "487f1f8c6cdf2297",
            "type": "leaf",
            "state": {
              "type": "tag",
              "state": {
                "sortOrder": "frequency",
                "useHierarchy": true
              }
            }
          },
          {
            "id": "7c63e09667e00ae6",
            "type": "leaf",
            "state": {
              "type": "outline",
              "state": {
                "file": "4 - Webpack & 工具链/babel原理综述.md"
              }
            }
          },
          {
            "id": "954724f60efb26e3",
            "type": "leaf",
            "state": {
              "type": "juggl_nodes",
              "state": {}
            }
          },
          {
            "id": "79225afb80f78aa9",
            "type": "leaf",
            "state": {
              "type": "juggl_style",
              "state": {}
            }
          },
          {
            "id": "1757ff0f731e57b5",
            "type": "leaf",
            "state": {
              "type": "advanced-tables-toolbar",
              "state": {}
            }
          }
        ],
        "currentTab": 3
      }
    ],
    "direction": "horizontal",
    "width": 226.5
  },
  "left-ribbon": {
    "hiddenItems": {
      "switcher:Open quick switcher": false,
      "graph:Open graph view": false,
      "canvas:Create new canvas": false,
      "daily-notes:Open today's daily note": false,
      "templates:Insert template": false,
      "command-palette:Open command palette": false,
      "juggl:Juggl global graph": false,
      "table-editor-obsidian:Advanced Tables Toolbar": false,
      "obsidian42-brat:BRAT": false,
      "obsidian-excalidraw-plugin:Create new drawing": false
    }
  },
  "active": "ae72f1b6abe14242",
  "lastOpenFiles": [
    "Excalidraw/基础 2024-02-13 20.03.24.excalidraw.md",
    "4 - Webpack & 工具链/babel原理综述.md",
    "3 - VUE/vue3-aureole.md",
    "3 - VUE/Vue基础.md",
    "Excalidraw/Vue基础 2024-06-06 17.25.54.excalidraw.md",
    "4 - Webpack & 工具链/webpack基础.md",
    "1 - JS/3- 浏览器原理.md",
    "1 - JS/2- 前端性能优化.md",
    "1 - JS/1- JS基础.md",
    "3 - VUE/reactivity/3- effect具备的能力.md",
    "3 - VUE/reactivity/4 - ref相关.md",
    "3 - VUE/reactivity/1- Proxy与响应式对象.md",
    "3 - VUE/reactivity/2- 收集依赖与触发依赖.md",
    "7 - 前端全链路监控/2 - 数据结构设计.md",
    "7 - 前端全链路监控/1 - 监控流程设计.md",
    "README.md",
    "5 - 计算机网络/1 - 计网基础.md",
    "6 - 低代码项目/2 - 低代码CLI工具.md",
    "6 - 低代码项目/1 - 流程综述.md",
    "image/img 前端全链路监控/Pasted image 20240523163648.png",
    "Untitled 1.md",
    "Untitled",
    "Untitled.md",
    "Excalidraw/1- JS基础 2024-05-20 21.18.24.excalidraw.md",
    "8 - 前端跨端技术/Untitled.md",
    "8 - 前端跨端技术",
    "7 - 前端全链路监控/test.md",
    "Learning-and-Knowledge-Accumulation",
    "image/img 前端全链路监控",
    "image/img 前端全链路监控/Pasted image 20240509135340.png",
    "7 - 前端全链路监控",
    "2 - CSS/1 - CSS基础.md",
    "image/img JS基础/Pasted image 20240424114625.png",
    "image/img 前端性能优化/Pasted image 20240423222513.png",
    "image/img 浏览器原理/Pasted image 20240423131522.png",
    "image/img 浏览器原理/Pasted image 20240423130235.png",
    "image/img JS基础/Pasted image 20240325214241.png",
    "Pasted image 20240423130111.png",
    "6 - 低代码项目",
    "image/img 计网基础/Pasted image 20240213191641.png",
    "image/img 计网基础/Pasted image 20240325214040.png",
    "Excalidraw/1- JS基础方法与属性 2024-02-07 21.17.00.excalidraw.md",
    "image/img webpack基础",
    "1 - JS/img 浏览器原理",
    "4 - Webpack & 工具链/img webpack基础",
    "1 - JS/img JS基础",
    "Untitled.canvas"
  ]
}